MANIFEST.in
README
setup.cfg
setup.py
atompiglet/__init__.py
atompiglet/auth.py
atompiglet/collection.py
atompiglet/entry.py
atompiglet/errors.py
atompiglet/server.py
atompiglet/workspace.py
atompiglet/xmlutil.py
atompiglet.egg-info/PKG-INFO
atompiglet.egg-info/SOURCES.txt
atompiglet.egg-info/dependency_links.txt
atompiglet.egg-info/entry_points.txt
atompiglet.egg-info/not-zip-safe
atompiglet.egg-info/requires.txt
atompiglet.egg-info/top_level.txt
atompiglet/ext/__init__.py
atompiglet/ext/kurt.py
atompiglet/ext/rdf.py
atompiglet/tests/__init__.py
atompiglet/tests/helpers.py
atompiglet/tests/test_collection.py
atompiglet/tests/test_entry.py
atompiglet/tests/test_etags.py
atompiglet/tests/test_kurt_book.py
atompiglet/tests/test_kurt_docbook.py
atompiglet/tests/test_kurt_utils.py
atompiglet/tests/test_misc.py
atompiglet/tests/test_rdf_utils.py
atompiglet/tests/test_server.py
atompiglet/tests/test_workspace.py
atompiglet/xslt/__init__.py
atompiglet/xslt/atom_to_legacy_rdf.xsl
atompiglet/xslt/atom_to_rdf.xsl