Metadata-Version: 1.0
Name: atompiglet
Version: 0.8.1
Summary: AtomPiglet is a library for interacting with AtomPub servers.
Home-page: http://bitbucket.org/gavin/atom-piglet/
Author: Keith Fahlgren
Author-email: abdelazer@gmail.com
License: Apache
Keywords: atompub
Platform: UNKNOWN
